streamlana/__init__.py
streamlana/app_state.py
streamlana/chart_helpers.py
streamlana/envs.py
streamlana/side_bar_util.py
streamlana/streamlana.ico
streamlana/streamlana.png
streamlana/util.py
streamlana/util_test.py
streamlana-0.1.4.dist-info/LICENSE
streamlana-0.1.4.dist-info/METADATA
streamlana-0.1.4.dist-info/WHEEL
streamlana-0.1.4.dist-info/RECORD
