Metadata-Version: 2.1
Name: streamlana
Version: 0.1.4
Summary: Business Intelligence as Configuration
License: MIT
Author: vishnu rao
Requires-Python: >=3.11,<4.0
Classifier: License :: OSI Approved :: MIT License
Classifier: Programming Language :: Python :: 3
Classifier: Programming Language :: Python :: 3.11
Requires-Dist: datasketches (==5.1.1)
Requires-Dist: duckdb (==1.3.0)
Requires-Dist: numpy (>=2.3.0,<3.0.0)
Requires-Dist: pandas (>=2.3.0,<3.0.0)
Requires-Dist: plotly (>=6.1.2,<7.0.0)
Requires-Dist: pyyaml (==6.0.2)
Requires-Dist: streamlit (==1.46.0)
Requires-Dist: tabulate (>=0.9.0,<0.10.0)
